souschef/__init__.py
souschef/assessment.py
souschef/ci/__init__.py
souschef/ci/common.py
souschef/ci/github_actions.py
souschef/ci/gitlab_ci.py
souschef/ci/jenkins_pipeline.py
souschef/cli.py
souschef/converters/__init__.py
souschef/converters/cookbook_specific.py
souschef/converters/cookbook_specific.py.backup
souschef/converters/habitat.py
souschef/converters/playbook.py
souschef/converters/resource.py
souschef/converters/template.py
souschef/core/__init__.py
souschef/core/constants.py
souschef/core/errors.py
souschef/core/metrics.py
souschef/core/path_utils.py
souschef/core/ruby_utils.py
souschef/core/validation.py
souschef/deployment.py
souschef/filesystem/__init__.py
souschef/filesystem/operations.py
souschef/parsers/__init__.py
souschef/parsers/attributes.py
souschef/parsers/habitat.py
souschef/parsers/inspec.py
souschef/parsers/metadata.py
souschef/parsers/recipe.py
souschef/parsers/resource.py
souschef/parsers/template.py
souschef/profiling.py
souschef/server.py
souschef/ui/__init__.py
souschef/ui/app.py
souschef/ui/health_check.py
souschef/ui/pages/ai_settings.py
souschef/ui/pages/cookbook_analysis.py
souschef/ui/pages/validation_reports.py
mcp_souschef-3.0.0.dist-info/METADATA
mcp_souschef-3.0.0.dist-info/WHEEL
mcp_souschef-3.0.0.dist-info/entry_points.txt
mcp_souschef-3.0.0.dist-info/licenses/LICENSE
mcp_souschef-3.0.0.dist-info/RECORD
