Metadata-Version: 2.4
Name: mcp-souschef
Version: 3.0.0
Summary: AI-powered MCP server for Chef to Ansible conversion
License: MIT
License-File: LICENSE
Keywords: chef,ansible,migration,infrastructure,automation,mcp,ai,conversion
Author: SousChef Contributors
Requires-Python: >=3.13,<4.0
Classifier: Development Status :: 4 - Beta
Classifier: Intended Audience :: Developers
Classifier: Intended Audience :: System Administrators
Classifier: License :: OSI Approved :: MIT License
Classifier: Operating System :: OS Independent
Classifier: Programming Language :: Python :: 3
Classifier: Programming Language :: Python :: 3.13
Classifier: Programming Language :: Python :: 3.14
Classifier: Topic :: Software Development :: Libraries :: Python Modules
Classifier: Topic :: System :: Systems Administration
Classifier: Topic :: Utilities
Provides-Extra: ui
Requires-Dist: anthropic (>=0.75.0)
Requires-Dist: click (>=8.1.0)
Requires-Dist: mcp (>=1.25.0)
Requires-Dist: openai (>=1.0.0)
Requires-Dist: pandas (>=2.0.0) ; extra == "ui"
Requires-Dist: plotly (>=5.0.0)
Requires-Dist: python-dotenv (>=1.2.1)
Requires-Dist: pyyaml (>=6.0.0)
Requires-Dist: streamlit (>=1.28.0)
Requires-Dist: zod (>=0.8.0)
Project-URL: Documentation, https://kpeacocke.github.io/souschef/
Project-URL: Homepage, https://github.com/kpeacocke/souschef
Project-URL: Repository, https://github.com/kpeacocke/souschef
